{
  "type": "FeatureCollection",
  "features": [
    {
      "type":"Feature",
      "properties":{
        "id":"ashikaga-gakko",
        "name":"足利学校",
        "radius":120,
        "quiz":"足利学校は日本最古の何？（ヒント：学びの場）",
        "answer":"学校（学問所）"
      },
      "geometry":{"type":"Point","coordinates":[139.4500,36.3400]}
    },
    {
      "type":"Feature",
      "properties":{
        "id":"bannaji",
        "name":"鑁阿寺",
        "radius":120,
        "quiz":"鑁阿寺本堂は何時代の国宝？",
        "answer":"鎌倉時代"
      },
      "geometry":{"type":"Point","coordinates":[139.4520,36.3350]}
    }
  ]
}
